flower/__init__.py
flower/__main__.py
flower/app.py
flower/command.py
flower/events.py
flower/options.py
flower/urls.py
flower/api/__init__.py
flower/api/control.py
flower/api/events.py
flower/api/tasks.py
flower/api/workers.py
flower/static/favicon.ico
flower/static/swagger.json
flower/static/css/bootstrap-datetimepicker.min.css
flower/static/css/bootstrap-responsive.css
flower/static/css/bootstrap-responsive.min.css
flower/static/css/bootstrap.css
flower/static/css/bootstrap.min.css
flower/static/css/flower.css
flower/static/css/jquery-ui.css
flower/static/css/jquery.dataTables.buttons.min.css
flower/static/css/jquery.dataTables.colReorder.min.css
flower/static/css/jquery.dataTables.css
flower/static/css/jquery.dataTables.min.css
flower/static/css/jquery.dataTables.select.min.css
flower/static/css/rickshaw.min.css
flower/static/css/images/ui-bg_flat_0_aaaaaa_40x100.png
flower/static/css/images/ui-bg_flat_75_ffffff_40x100.png
flower/static/css/images/ui-bg_glass_55_fbf9ee_1x400.png
flower/static/css/images/ui-bg_glass_65_ffffff_1x400.png
flower/static/css/images/ui-bg_glass_75_dadada_1x400.png
flower/static/css/images/ui-bg_glass_75_e6e6e6_1x400.png
flower/static/css/images/ui-bg_glass_95_fef1ec_1x400.png
flower/static/css/images/ui-bg_highlight-soft_75_cccccc_1x100.png
flower/static/css/images/ui-icons_222222_256x240.png
flower/static/css/images/ui-icons_2e83ff_256x240.png
flower/static/css/images/ui-icons_454545_256x240.png
flower/static/css/images/ui-icons_888888_256x240.png
flower/static/css/images/ui-icons_cd0a0a_256x240.png
flower/static/img/apple-touch-icon-114-precomposed.png
flower/static/img/apple-touch-icon-144-precomposed.png
flower/static/img/apple-touch-icon-57-precomposed.png
flower/static/img/apple-touch-icon-72-precomposed.png
flower/static/img/datatable_sort_asc.png
flower/static/img/datatable_sort_asc_disabled.png
flower/static/img/datatable_sort_both.png
flower/static/img/datatable_sort_desc.png
flower_with_timeline-0.9.3.2.dist-info/LICENSE
flower_with_timeline-0.9.3.2.dist-info/METADATA
flower_with_timeline-0.9.3.2.dist-info/WHEEL
flower_with_timeline-0.9.3.2.dist-info/entry_points.txt
flower_with_timeline-0.9.3.2.dist-info/top_level.txt
flower_with_timeline-0.9.3.2.dist-info/RECORD
