Metadata-Version: 2.1
Name: flower-with-timeline
Version: 0.9.3.2
Summary: Celery Flower - with Timeline page
Home-page: https://github.com/mher/flower
Author: Mher Movsisyan
Author-email: mher.movsisyan@gmail.com
License: BSD
Platform: UNKNOWN
Classifier: Development Status :: 4 - Beta
Classifier: Intended Audience :: Developers
Classifier: License :: OSI Approved :: BSD License
Classifier: Topic :: System :: Distributed Computing
Classifier: Programming Language :: Python
Classifier: Programming Language :: Python :: 2
Classifier: Programming Language :: Python :: 2.7
Classifier: Programming Language :: Python :: 3
Classifier: Programming Language :: Python :: 3.3
Classifier: Programming Language :: Python :: 3.4
Classifier: Programming Language :: Python :: 3.5
Classifier: Programming Language :: Python :: 3.6
Classifier: Programming Language :: Python :: Implementation :: CPython
Classifier: Programming Language :: Python :: Implementation :: PyPy
Classifier: Operating System :: OS Independent
Requires-Dist: celery (>=3.1.0)
Requires-Dist: tornado (<6.0.0,>=4.2.0)
Requires-Dist: babel (<3.0.0,>=1.0)
Requires-Dist: pytz
Requires-Dist: futures ; python_version == "2.7"
